tools/__init__.py
tools/data_factory.py
tools/downloader.py
tools/logger.py
tools/multithread.py
tools/queue.py
tools/timer.py
tools/web_crawler.py
tools/writer.py
tfuc-1.0.9.dist-info/LICENSE
tfuc-1.0.9.dist-info/METADATA
tfuc-1.0.9.dist-info/WHEEL
tfuc-1.0.9.dist-info/top_level.txt
tfuc-1.0.9.dist-info/RECORD
