Metadata-Version: 2.1
Name: tfuc
Version: 1.0.9
Summary: some useful tools
Home-page: https://github.com/gitduk/tfuc.git
Author: dongkai
Author-email: wdkany@qq.com
License: UNKNOWN
Keywords: selenium,bs4,web_craw
Platform: UNKNOWN
Requires-Dist: sqlalchemy
Requires-Dist: xlrd
Requires-Dist: xlsxwriter
Requires-Dist: openpyxl
Requires-Dist: urllib3
Requires-Dist: bs4
Requires-Dist: fake-useragent
Requires-Dist: selenium
Requires-Dist: requests
